openmixup/__init__.py
openmixup/version.py
openmixup/apis/__init__.py
openmixup/apis/test.py
openmixup/apis/train.py
openmixup/core/__init__.py
openmixup/core/export/__init__.py
openmixup/core/export/test.py
openmixup/core/hooks/__init__.py
openmixup/core/hooks/addtional_scheduler.py
openmixup/core/hooks/builder.py
openmixup/core/hooks/deepcluster_automix_hook.py
openmixup/core/hooks/deepcluster_hook.py
openmixup/core/hooks/ema_hook.py
openmixup/core/hooks/extractor.py
openmixup/core/hooks/lr_scheduler.py
openmixup/core/hooks/momentum_hook.py
openmixup/core/hooks/odc_hook.py
openmixup/core/hooks/optimizer_hook.py
openmixup/core/hooks/precise_bn_hook.py
openmixup/core/hooks/registry.py
openmixup/core/hooks/save_hook.py
openmixup/core/hooks/selfsup_metric_hook.py
openmixup/core/hooks/swav_hook.py
openmixup/core/hooks/validate_hook.py
openmixup/core/optimizers/__init__.py
openmixup/core/optimizers/adabelief.py
openmixup/core/optimizers/adabound.py
openmixup/core/optimizers/adafactor.py
openmixup/core/optimizers/adahessian.py
openmixup/core/optimizers/adamp.py
openmixup/core/optimizers/adan.py
openmixup/core/optimizers/builder.py
openmixup/core/optimizers/constructor.py
openmixup/core/optimizers/lamb.py
openmixup/core/optimizers/lars.py
openmixup/core/optimizers/lion.py
openmixup/core/optimizers/madgrad.py
openmixup/core/optimizers/nvnovograd.py
openmixup/core/optimizers/sgdp.py
openmixup/core/optimizers/sophia.py
openmixup/datasets/__init__.py
openmixup/datasets/base.py
openmixup/datasets/beit_mim.py
openmixup/datasets/builder.py
openmixup/datasets/classification.py
openmixup/datasets/contrastive.py
openmixup/datasets/dataset_wrappers.py
openmixup/datasets/deepcluster.py
openmixup/datasets/deepcluster_contrastive.py
openmixup/datasets/extraction.py
openmixup/datasets/masked_image.py
openmixup/datasets/multi_view.py
openmixup/datasets/registry.py
openmixup/datasets/regression.py
openmixup/datasets/relative_loc.py
openmixup/datasets/rotation_pred.py
openmixup-0.2.9.dist-info/LICENSE
openmixup-0.2.9.dist-info/METADATA
openmixup-0.2.9.dist-info/WHEEL
openmixup-0.2.9.dist-info/top_level.txt
openmixup-0.2.9.dist-info/RECORD
