Metadata-Version: 2.1
Name: openmixup
Version: 0.2.9
Summary: Mixup for Supervision, Semi- and Self-Supervision Learning Toolbox and Benchmark
Home-page: https://github.com/Westlake-AI/openmixup
Author: CAIRI Westlake University Contributors
Author-email: lisiyuan@westlake.edu.com
License: Apache License 2.0
Keywords: computer vision,image classification,mixup classification,semi- and self-supervised learning
Classifier: Development Status :: 4 - Beta
Classifier: License :: OSI Approved :: Apache Software License
Classifier: Operating System :: OS Independent
Classifier: Programming Language :: Python :: 3
Classifier: Programming Language :: Python :: 3.6
Classifier: Programming Language :: Python :: 3.7
Classifier: Programming Language :: Python :: 3.8
Classifier: Programming Language :: Python :: 3.9
Classifier: Programming Language :: Python :: 3.10
Classifier: Programming Language :: Python :: 3.11
Classifier: Topic :: Scientific/Engineering :: Artificial Intelligence
License-File: LICENSE
Requires-Dist: attrs
Requires-Dist: einops
Requires-Dist: importlib-metadata
Requires-Dist: matplotlib
Requires-Dist: mmcv-full (<=1.7.2,>=1.4.7)
Requires-Dist: numpy
Requires-Dist: opencv-python
Requires-Dist: packaging
Requires-Dist: pandas
Requires-Dist: scipy
Requires-Dist: scikit-learn
Requires-Dist: seaborn
Requires-Dist: six
Requires-Dist: tensorboard
Requires-Dist: timm
Requires-Dist: tqdm
Provides-Extra: all
Requires-Dist: albumentations (>=0.3.2) ; extra == 'all'
Requires-Dist: faiss-gpu (>=1.6.1) ; extra == 'all'
Requires-Dist: grad-cam (>=1.3.7) ; extra == 'all'
Requires-Dist: gco (==1.0.1) ; extra == 'all'
Requires-Dist: opencv-contrib-python ; extra == 'all'
Requires-Dist: requests ; extra == 'all'
Requires-Dist: scikit-image ; extra == 'all'
Requires-Dist: attrs ; extra == 'all'
Requires-Dist: einops ; extra == 'all'
Requires-Dist: importlib-metadata ; extra == 'all'
Requires-Dist: matplotlib ; extra == 'all'
Requires-Dist: mmcv-full (<=1.7.2,>=1.4.7) ; extra == 'all'
Requires-Dist: numpy ; extra == 'all'
Requires-Dist: opencv-python ; extra == 'all'
Requires-Dist: packaging ; extra == 'all'
Requires-Dist: pandas ; extra == 'all'
Requires-Dist: scipy ; extra == 'all'
Requires-Dist: scikit-learn ; extra == 'all'
Requires-Dist: seaborn ; extra == 'all'
Requires-Dist: six ; extra == 'all'
Requires-Dist: tensorboard ; extra == 'all'
Requires-Dist: timm ; extra == 'all'
Requires-Dist: tqdm ; extra == 'all'
Requires-Dist: asynctest ; extra == 'all'
Requires-Dist: codecov ; extra == 'all'
Requires-Dist: flake8 ; extra == 'all'
Requires-Dist: isort ; extra == 'all'
Requires-Dist: pytest ; extra == 'all'
Requires-Dist: pytest-cov ; extra == 'all'
Requires-Dist: pytest-runner ; extra == 'all'
Requires-Dist: xdoctest (>=0.10.0) ; extra == 'all'
Requires-Dist: yapf ; extra == 'all'
Requires-Dist: kwarray ; extra == 'all'
Provides-Extra: mim
Requires-Dist: mmcls (>=0.21.0) ; extra == 'mim'
Requires-Dist: mmcv-full (<=1.7.2,>=1.4.7) ; extra == 'mim'
Requires-Dist: mmengine (<1.0.0,>=0.4.0) ; extra == 'mim'
Requires-Dist: mmdet (>=2.16.0) ; extra == 'mim'
Requires-Dist: mmsegmentation (>=0.20.2) ; extra == 'mim'
Provides-Extra: optional
Requires-Dist: albumentations (>=0.3.2) ; extra == 'optional'
Requires-Dist: faiss-gpu (>=1.6.1) ; extra == 'optional'
Requires-Dist: grad-cam (>=1.3.7) ; extra == 'optional'
Requires-Dist: gco (==1.0.1) ; extra == 'optional'
Requires-Dist: opencv-contrib-python ; extra == 'optional'
Requires-Dist: requests ; extra == 'optional'
Requires-Dist: scikit-image ; extra == 'optional'
Provides-Extra: tests
Requires-Dist: asynctest ; extra == 'tests'
Requires-Dist: codecov ; extra == 'tests'
Requires-Dist: flake8 ; extra == 'tests'
Requires-Dist: isort ; extra == 'tests'
Requires-Dist: pytest ; extra == 'tests'
Requires-Dist: pytest-cov ; extra == 'tests'
Requires-Dist: pytest-runner ; extra == 'tests'
Requires-Dist: xdoctest (>=0.10.0) ; extra == 'tests'
Requires-Dist: yapf ; extra == 'tests'
Requires-Dist: kwarray ; extra == 'tests'
